{
  "es": {
    "title": "Hobby",
    "subtitle": "Videojuegos creados con cariño y sin fines comerciales ❤️",
    "hobbies": [
      {
        "title": "Flappy Bird",
        "description": "Flappy Bird es un videojuego arcade en el que controlas un pájaro que debe volar entre tuberías sin chocarse",
        "icon": "🐤",
        "images": [
          "images/games/flappy_1.png",
          "images/games/flappy_2.png",
          "images/games/flappy_3.png"
        ],
        "url": "https://pabllopf.itch.io/alissampleflappybird"
      },
      {
        "title": "Asteroid",
        "description": "Juego arcade donde controlas una nave espacial que debe destruir asteroides y platillos voladores",
        "icon": "🚀",
        "images": [
          "images/games/asteroid_1.png",
          "images/games/asteroid_2.png",
          "images/games/asteroid_3.png"
        ],
        "url": "https://pabllopf.itch.io/alissampleasteroid"
      },
      {
        "title": "OpenGl",
        "description": "Ejemplos no comercial creado para demostrar las capacidades de Alis",
        "icon": "🕹️",
        "images": [
          "images/games/opengl_1.png",
          "images/games/opengl_2.png",
          "images/games/opengl_3.png",
          "images/games/opengl_4.png"
        ],
        "url": "https://pabllopf.itch.io/alissampleopengl"
      }
    ]
  },
  "en": {
    "title": "Hobby",
    "subtitle": "Videogames created with love and without commercial goals ❤️",
    "hobbies": [
      {
        "title": "Flappy Bird",
        "description": "Flappy Bird is an arcade-style game where you control a bird that must fly between pipes without crashing",
        "icon": "🐤",
        "images": [
          "images/games/flappy_1.png",
          "images/games/flappy_2.png",
          "images/games/flappy_3.png"
        ],
        "url": "https://pabllopf.itch.io/alissampleflappybird"
      },
     {
        "title": "Asteroid",
        "description": "Asteroids is a classic arcade video game where you control a spaceship that must destroy asteroids and flying saucers while avoiding collisions",
        "icon": "🚀",
        "images": [
          "images/games/asteroid_1.png",
          "images/games/asteroid_2.png",
          "images/games/asteroid_3.png"
        ],
        "url": "https://pabllopf.itch.io/alissampleasteroid"
      },
      {
        "title": "OpenGl",
        "description": "Samples non-commercial example created to demonstrate the capabilities of Alis",
        "icon": "🕹️",
        "images": [
          "images/games/opengl_1.png",
          "images/games/opengl_2.png",
          "images/games/opengl_3.png",
          "images/games/opengl_4.png"
        ],
        "url": "https://pabllopf.itch.io/alissampleopengl"
      }
    ]
  }
}
